LICENSE.txt
MANIFEST.in
README.md
setup.py
StrikePy/RunModels.py
StrikePy/__init__.py
StrikePy/options.py
StrikePy/strike_goldd.py
StrikePy.egg-info/PKG-INFO
StrikePy.egg-info/SOURCES.txt
StrikePy.egg-info/dependency_links.txt
StrikePy.egg-info/requires.txt
StrikePy.egg-info/top_level.txt
StrikePy/custom_options/__init__.py
StrikePy/custom_options/options_C2M.py
StrikePy/custom_options/options_HIV.py
StrikePy/custom_options/options_HIV_1.py
StrikePy/custom_options/options_JAKSTAT.py
StrikePy/custom_options/options_MAPK.py
StrikePy/custom_options/options_PK.py
StrikePy/custom_options/options_SIWR.py
StrikePy/custom_options/options_p53.py
StrikePy/custom_options/options_phos.py
StrikePy/custom_options/options_sirs.py
StrikePy/custom_options/options_tumor.py
StrikePy/doc/StrikePy_manual.pdf
StrikePy/functions/__init__.py
StrikePy/functions/elim_and_recalc.py
StrikePy/functions/rationalize.py
StrikePy/models/1A_integral.py
StrikePy/models/1B_prop_integral.py
StrikePy/models/1C_nonlinear.py
StrikePy/models/1D_BIG.py
StrikePy/models/Arabidopsis.py
StrikePy/models/BIG_known_input.py
StrikePy/models/Bolie.py
StrikePy/models/C2M.py
StrikePy/models/C2M_2outputs.py
StrikePy/models/C2M_unknown_input_known_b.py
StrikePy/models/C2M_unknown_input_known_b_k1e.py
StrikePy/models/CR.py
StrikePy/models/HIV.py
StrikePy/models/HIV_1.py
StrikePy/models/JAKSTAT.py
StrikePy/models/MAPK.py
StrikePy/models/PK.py
StrikePy/models/SIWR.py
StrikePy/models/TS_unknown_inputs_reparameterized.py
StrikePy/models/__init__.py
StrikePy/models/p53.py
StrikePy/models/phos.py
StrikePy/models/sirs.py
StrikePy/models/tumor.py