Metadata-Version: 2.1
Name: StrikePy
Version: 1.0
Summary: A package for observability and identifiability analysis of non-linear systems 
Home-page: https://github.com/afvillaverde/StrikePy
Author: David Rey Rostro
Author-email: davidreyrostro@gmail.com
License: UNKNOWN
Download-URL: https://github.com/afvillaverde/StrikePy
Keywords: StrikePy,STRIKE-GOLDD,analysis,non-linear,observability,identifiability,dynamic modelling,biosystems
Platform: UNKNOWN
Classifier: Programming Language :: Python :: 3.9
Classifier: License :: OSI Approved :: GNU General Public License v3 (GPLv3)
Classifier: Operating System :: OS Independent
Requires-Python: >=3.9
License-File: LICENSE.txt
